{"v":"5.12.1","fr":60,"ip":0,"op":90,"w":512,"h":512,"nm":"My_lottie101","ddd":0,"assets":[],"layers":[{"ddd":0,"ind":1,"ty":4,"nm":"Capa 4","sr":1,"ks":{"o":{"a":1,"k":[{"i":{"x":[0.667],"y":[1]},"o":{"x":[0.333],"y":[0]},"t":71,"s":[100]},{"t":81,"s":[0]}],"ix":11},"r":{"a":0,"k":0,"ix":10},"p":{"a":1,"k":[{"i":{"x":0.667,"y":1},"o":{"x":0.333,"y":0},"t":34,"s":[190.271,169.899,0],"to":[0,0,0],"ti":[0,0,0]},{"t":81,"s":[201.071,182.859,0]}],"ix":2,"l":2},"a":{"a":0,"k":[50.5,7,0],"ix":1,"l":2},"s":{"a":1,"k":[{"i":{"x":[0.667,0.667,0.667],"y":[1,1,1]},"o":{"x":[0.333,0.333,0.333],"y":[0,0,0]},"t":34,"s":[0,0,100]},{"t":51,"s":[43.2,43.2,100]}],"ix":6,"l":2}},"ao":0,"shapes":[{"ty":"gr","it":[{"ind":0,"ty":"sh","ix":1,"ks":{"a":0,"k":{"i":[[-14.278,-38.721],[0,0],[-1.917,0],[-0.663,1.801],[0,0],[-38.716,14.275],[0,0],[0,1.917],[1.798,0.663],[0,0],[14.275,38.716],[0,0],[1.917,0],[0.663,-1.798],[0,0],[38.718,-14.278],[0,0],[0,-1.917],[-1.798,-0.663],[0,0]],"o":[[0,0],[0.663,1.801],[1.917,0],[0,0],[14.278,-38.718],[0,0],[1.798,-0.663],[0,-1.917],[0,0],[-38.716,-14.278],[0,0],[-0.663,-1.798],[-1.917,0],[0,0],[-14.278,38.716],[0,0],[-1.798,0.663],[0,1.917],[0,0],[38.718,14.275]],"v":[[-21.932,105.446],[-4.293,153.273],[0.001,156.267],[4.295,153.273],[21.935,105.446],[105.45,21.931],[153.277,4.291],[156.269,-0.003],[153.277,-4.297],[105.447,-21.936],[21.935,-105.449],[4.295,-153.275],[0.001,-156.267],[-4.293,-153.275],[-21.932,-105.449],[-105.447,-21.936],[-153.277,-4.297],[-156.269,-0.003],[-153.277,4.291],[-105.45,21.931]],"c":true},"ix":2},"nm":"Path 1","mn":"ADBE Vector Shape - Group","hd":false},{"ty":"gf","o":{"a":0,"k":100,"ix":10},"r":1,"bm":0,"g":{"p":3,"k":{"a":0,"k":[0,0.142,0.469,1,0.498,0.071,0.66,1,1,0,0.852,1],"ix":9}},"s":{"a":0,"k":[-84,146],"ix":5},"e":{"a":0,"k":[56,-76],"ix":6},"t":1,"nm":"Gradient Fill 1","mn":"ADBE Vector Graphic - G-Fill","hd":false},{"ty":"tr","p":{"a":0,"k":[50.5,7],"ix":2},"a":{"a":0,"k":[0,0],"ix":1},"s":{"a":0,"k":[30,30],"ix":3},"r":{"a":0,"k":0,"ix":6},"o":{"a":0,"k":100,"ix":7},"sk":{"a":0,"k":0,"ix":4},"sa":{"a":0,"k":0,"ix":5},"nm":"Transform"}],"nm":"Group 1","np":2,"cix":2,"bm":0,"ix":1,"mn":"ADBE Vector Group","hd":false}],"ip":34,"op":334,"st":34,"ct":1,"bm":0},{"ddd":0,"ind":2,"ty":4,"nm":"Capa 3","sr":1,"ks":{"o":{"a":1,"k":[{"i":{"x":[0.667],"y":[1]},"o":{"x":[0.333],"y":[0]},"t":64,"s":[100]},{"t":74,"s":[0]}],"ix":11},"r":{"a":0,"k":0,"ix":10},"p":{"a":1,"k":[{"i":{"x":0.667,"y":1},"o":{"x":0.333,"y":0},"t":27,"s":[227.607,184.102,0],"to":[0,0,0],"ti":[0,0,0]},{"t":74,"s":[245.607,205.702,0]}],"ix":2,"l":2},"a":{"a":0,"k":[50.5,7,0],"ix":1,"l":2},"s":{"a":1,"k":[{"i":{"x":[0.667,0.667,0.667],"y":[1,1,1]},"o":{"x":[0.333,0.333,0.333],"y":[0,0,0]},"t":27,"s":[0,0,100]},{"t":44,"s":[72,72,100]}],"ix":6,"l":2}},"ao":0,"shapes":[{"ty":"gr","it":[{"ind":0,"ty":"sh","ix":1,"ks":{"a":0,"k":{"i":[[-14.278,-38.721],[0,0],[-1.917,0],[-0.663,1.801],[0,0],[-38.716,14.275],[0,0],[0,1.917],[1.798,0.663],[0,0],[14.275,38.716],[0,0],[1.917,0],[0.663,-1.798],[0,0],[38.718,-14.278],[0,0],[0,-1.917],[-1.798,-0.663],[0,0]],"o":[[0,0],[0.663,1.801],[1.917,0],[0,0],[14.278,-38.718],[0,0],[1.798,-0.663],[0,-1.917],[0,0],[-38.716,-14.278],[0,0],[-0.663,-1.798],[-1.917,0],[0,0],[-14.278,38.716],[0,0],[-1.798,0.663],[0,1.917],[0,0],[38.718,14.275]],"v":[[-21.932,105.446],[-4.293,153.273],[0.001,156.267],[4.295,153.273],[21.935,105.446],[105.45,21.931],[153.277,4.291],[156.269,-0.003],[153.277,-4.297],[105.447,-21.936],[21.935,-105.449],[4.295,-153.275],[0.001,-156.267],[-4.293,-153.275],[-21.932,-105.449],[-105.447,-21.936],[-153.277,-4.297],[-156.269,-0.003],[-153.277,4.291],[-105.45,21.931]],"c":true},"ix":2},"nm":"Path 1","mn":"ADBE Vector Shape - Group","hd":false},{"ty":"gf","o":{"a":0,"k":100,"ix":10},"r":1,"bm":0,"g":{"p":3,"k":{"a":0,"k":[0,0.142,0.469,1,0.498,0.071,0.66,1,1,0,0.852,1],"ix":9}},"s":{"a":0,"k":[-84,146],"ix":5},"e":{"a":0,"k":[56,-76],"ix":6},"t":1,"nm":"Gradient Fill 1","mn":"ADBE Vector Graphic - G-Fill","hd":false},{"ty":"tr","p":{"a":0,"k":[50.5,7],"ix":2},"a":{"a":0,"k":[0,0],"ix":1},"s":{"a":0,"k":[30,30],"ix":3},"r":{"a":0,"k":0,"ix":6},"o":{"a":0,"k":100,"ix":7},"sk":{"a":0,"k":0,"ix":4},"sa":{"a":0,"k":0,"ix":5},"nm":"Transform"}],"nm":"Group 1","np":2,"cix":2,"bm":0,"ix":1,"mn":"ADBE Vector Group","hd":false}],"ip":27,"op":327,"st":27,"ct":1,"bm":0},{"ddd":0,"ind":3,"ty":4,"nm":"Capa 2","sr":1,"ks":{"o":{"a":1,"k":[{"i":{"x":[0.667],"y":[1]},"o":{"x":[0.333],"y":[0]},"t":46,"s":[100]},{"t":56,"s":[0]}],"ix":11},"r":{"a":0,"k":0,"ix":10},"p":{"a":1,"k":[{"i":{"x":0.667,"y":1},"o":{"x":0.333,"y":0},"t":9,"s":[184.512,220.787,0],"to":[0,0,0],"ti":[0,0,0]},{"t":56,"s":[204.512,244.787,0]}],"ix":2,"l":2},"a":{"a":0,"k":[50.5,7,0],"ix":1,"l":2},"s":{"a":1,"k":[{"i":{"x":[0.667,0.667,0.667],"y":[1,1,1]},"o":{"x":[0.333,0.333,0.333],"y":[0,0,0]},"t":9,"s":[0,0,100]},{"t":26,"s":[80,80,100]}],"ix":6,"l":2}},"ao":0,"shapes":[{"ty":"gr","it":[{"ind":0,"ty":"sh","ix":1,"ks":{"a":0,"k":{"i":[[-14.278,-38.721],[0,0],[-1.917,0],[-0.663,1.801],[0,0],[-38.716,14.275],[0,0],[0,1.917],[1.798,0.663],[0,0],[14.275,38.716],[0,0],[1.917,0],[0.663,-1.798],[0,0],[38.718,-14.278],[0,0],[0,-1.917],[-1.798,-0.663],[0,0]],"o":[[0,0],[0.663,1.801],[1.917,0],[0,0],[14.278,-38.718],[0,0],[1.798,-0.663],[0,-1.917],[0,0],[-38.716,-14.278],[0,0],[-0.663,-1.798],[-1.917,0],[0,0],[-14.278,38.716],[0,0],[-1.798,0.663],[0,1.917],[0,0],[38.718,14.275]],"v":[[-21.932,105.446],[-4.293,153.273],[0.001,156.267],[4.295,153.273],[21.935,105.446],[105.45,21.931],[153.277,4.291],[156.269,-0.003],[153.277,-4.297],[105.447,-21.936],[21.935,-105.449],[4.295,-153.275],[0.001,-156.267],[-4.293,-153.275],[-21.932,-105.449],[-105.447,-21.936],[-153.277,-4.297],[-156.269,-0.003],[-153.277,4.291],[-105.45,21.931]],"c":true},"ix":2},"nm":"Path 1","mn":"ADBE Vector Shape - Group","hd":false},{"ty":"gf","o":{"a":0,"k":100,"ix":10},"r":1,"bm":0,"g":{"p":3,"k":{"a":0,"k":[0,0.142,0.469,1,0.498,0.071,0.66,1,1,0,0.852,1],"ix":9}},"s":{"a":0,"k":[-84,146],"ix":5},"e":{"a":0,"k":[56,-76],"ix":6},"t":1,"nm":"Gradient Fill 1","mn":"ADBE Vector Graphic - G-Fill","hd":false},{"ty":"tr","p":{"a":0,"k":[50.5,7],"ix":2},"a":{"a":0,"k":[0,0],"ix":1},"s":{"a":0,"k":[30,30],"ix":3},"r":{"a":0,"k":0,"ix":6},"o":{"a":0,"k":100,"ix":7},"sk":{"a":0,"k":0,"ix":4},"sa":{"a":0,"k":0,"ix":5},"nm":"Transform"}],"nm":"Group 1","np":2,"cix":2,"bm":0,"ix":1,"mn":"ADBE Vector Group","hd":false}],"ip":9,"op":309,"st":9,"ct":1,"bm":0},{"ddd":0,"ind":4,"ty":4,"nm":"Capa 1","sr":1,"ks":{"o":{"a":1,"k":[{"i":{"x":[0.667],"y":[1]},"o":{"x":[0.333],"y":[0]},"t":37,"s":[100]},{"t":47,"s":[0]}],"ix":11},"r":{"a":0,"k":0,"ix":10},"p":{"a":1,"k":[{"i":{"x":0.667,"y":1},"o":{"x":0.333,"y":0},"t":0,"s":[243.432,241.691,0],"to":[0,0,0],"ti":[0,0,0]},{"t":47,"s":[268.432,271.691,0]}],"ix":2,"l":2},"a":{"a":0,"k":[50.5,7,0],"ix":1,"l":2},"s":{"a":1,"k":[{"i":{"x":[0.667,0.667,0.667],"y":[1,1,1]},"o":{"x":[0.333,0.333,0.333],"y":[0,0,0]},"t":0,"s":[0,0,100]},{"t":17,"s":[100,100,100]}],"ix":6,"l":2}},"ao":0,"shapes":[{"ty":"gr","it":[{"ind":0,"ty":"sh","ix":1,"ks":{"a":0,"k":{"i":[[-14.278,-38.721],[0,0],[-1.917,0],[-0.663,1.801],[0,0],[-38.716,14.275],[0,0],[0,1.917],[1.798,0.663],[0,0],[14.275,38.716],[0,0],[1.917,0],[0.663,-1.798],[0,0],[38.718,-14.278],[0,0],[0,-1.917],[-1.798,-0.663],[0,0]],"o":[[0,0],[0.663,1.801],[1.917,0],[0,0],[14.278,-38.718],[0,0],[1.798,-0.663],[0,-1.917],[0,0],[-38.716,-14.278],[0,0],[-0.663,-1.798],[-1.917,0],[0,0],[-14.278,38.716],[0,0],[-1.798,0.663],[0,1.917],[0,0],[38.718,14.275]],"v":[[-21.932,105.446],[-4.293,153.273],[0.001,156.267],[4.295,153.273],[21.935,105.446],[105.45,21.931],[153.277,4.291],[156.269,-0.003],[153.277,-4.297],[105.447,-21.936],[21.935,-105.449],[4.295,-153.275],[0.001,-156.267],[-4.293,-153.275],[-21.932,-105.449],[-105.447,-21.936],[-153.277,-4.297],[-156.269,-0.003],[-153.277,4.291],[-105.45,21.931]],"c":true},"ix":2},"nm":"Path 1","mn":"ADBE Vector Shape - Group","hd":false},{"ty":"gf","o":{"a":0,"k":100,"ix":10},"r":1,"bm":0,"g":{"p":3,"k":{"a":0,"k":[0,0.142,0.469,1,0.498,0.071,0.66,1,1,0,0.852,1],"ix":9}},"s":{"a":0,"k":[-84,146],"ix":5},"e":{"a":0,"k":[56,-76],"ix":6},"t":1,"nm":"Gradient Fill 1","mn":"ADBE Vector Graphic - G-Fill","hd":false},{"ty":"tr","p":{"a":0,"k":[50.5,7],"ix":2},"a":{"a":0,"k":[0,0],"ix":1},"s":{"a":0,"k":[30,30],"ix":3},"r":{"a":0,"k":0,"ix":6},"o":{"a":0,"k":100,"ix":7},"sk":{"a":0,"k":0,"ix":4},"sa":{"a":0,"k":0,"ix":5},"nm":"Transform"}],"nm":"Group 1","np":2,"cix":2,"bm":0,"ix":1,"mn":"ADBE Vector Group","hd":false}],"ip":0,"op":300,"st":0,"ct":1,"bm":0},{"ddd":0,"ind":5,"ty":4,"nm":"Lens ","sr":1,"ks":{"o":{"a":0,"k":100,"ix":11},"r":{"a":0,"k":0,"ix":10},"p":{"a":0,"k":[293,292,0],"ix":2,"l":2},"a":{"a":0,"k":[-3274.332,714.562,0],"ix":1,"l":2},"s":{"a":0,"k":[161,161,100],"ix":6,"l":2}},"ao":0,"shapes":[{"ty":"gr","it":[{"ty":"gr","it":[{"ind":0,"ty":"sh","ix":1,"ks":{"a":0,"k":{"i":[[0,0],[0,0]],"o":[[0,0],[0,0]],"v":[[-6.544,-6.544],[6.544,6.544]],"c":false},"ix":2},"nm":"Path 1","mn":"ADBE Vector Shape - Group","hd":false},{"ty":"st","c":{"a":0,"k":[0.01568627451,0.298039215686,0.81568627451,1],"ix":3},"o":{"a":0,"k":100,"ix":4},"w":{"a":0,"k":5,"ix":5},"lc":2,"lj":2,"bm":0,"nm":"Stroke 1","mn":"ADBE Vector Graphic - Stroke","hd":false},{"ty":"tr","p":{"a":0,"k":[0,0],"ix":2},"a":{"a":0,"k":[0,0],"ix":1},"s":{"a":0,"k":[100,100],"ix":3},"r":{"a":0,"k":0,"ix":6},"o":{"a":0,"k":100,"ix":7},"sk":{"a":0,"k":0,"ix":4},"sa":{"a":0,"k":0,"ix":5},"nm":"Transform"}],"nm":"Group 1","np":2,"cix":2,"bm":0,"ix":1,"mn":"ADBE Vector Group","hd":false},{"ty":"tr","p":{"a":0,"k":[-3188.195,795.674],"ix":2},"a":{"a":0,"k":[0,0],"ix":1},"s":{"a":0,"k":[100,100],"ix":3},"r":{"a":0,"k":0,"ix":6},"o":{"a":0,"k":100,"ix":7},"sk":{"a":0,"k":0,"ix":4},"sa":{"a":0,"k":0,"ix":5},"nm":"Transform"}],"nm":"Group 1","np":1,"cix":2,"bm":0,"ix":1,"mn":"ADBE Vector Group","hd":false},{"ty":"gr","it":[{"ty":"gr","it":[{"ind":0,"ty":"sh","ix":1,"ks":{"a":0,"k":{"i":[[0,0],[0,0]],"o":[[0,0],[0,0]],"v":[[10.855,10.855],[-10.855,-10.855]],"c":false},"ix":2},"nm":"Path 1","mn":"ADBE Vector Shape - Group","hd":false},{"ty":"st","c":{"a":0,"k":[0.01568627451,0.298039215686,0.81568627451,1],"ix":3},"o":{"a":0,"k":100,"ix":4},"w":{"a":0,"k":5,"ix":5},"lc":1,"lj":1,"ml":10,"bm":0,"nm":"Stroke 1","mn":"ADBE Vector Graphic - Stroke","hd":false},{"ty":"fl","c":{"a":0,"k":[1,1,1,1],"ix":4},"o":{"a":0,"k":100,"ix":5},"r":1,"bm":0,"nm":"Fill 1","mn":"ADBE Vector Graphic - Fill","hd":false},{"ty":"tr","p":{"a":0,"k":[-3249.623,739.272],"ix":2},"a":{"a":0,"k":[0,0],"ix":1},"s":{"a":0,"k":[100,100],"ix":3},"r":{"a":0,"k":0,"ix":6},"o":{"a":0,"k":100,"ix":7},"sk":{"a":0,"k":0,"ix":4},"sa":{"a":0,"k":0,"ix":5},"nm":"Transform"}],"nm":"Group 1","np":3,"cix":2,"bm":0,"ix":1,"mn":"ADBE Vector Group","hd":false},{"ty":"gr","it":[{"ind":0,"ty":"sh","ix":1,"ks":{"a":0,"k":{"i":[[5.995,-5.995],[0,0],[5.995,5.995],[0,0],[-5.995,5.995],[0,0],[-5.995,-5.995],[0,0]],"o":[[0,0],[-5.995,5.995],[0,0],[-5.995,-5.995],[0,0],[5.995,-5.995],[0,0],[5.995,5.995]],"v":[[32.729,32.729],[32.729,32.729],[11.019,32.729],[-32.729,-11.019],[-32.729,-32.729],[-32.729,-32.729],[-11.019,-32.729],[32.729,11.019]],"c":true},"ix":2},"nm":"Path 1","mn":"ADBE Vector Shape - Group","hd":false},{"ty":"st","c":{"a":0,"k":[0.01568627451,0.298039215686,0.81568627451,1],"ix":3},"o":{"a":0,"k":100,"ix":4},"w":{"a":0,"k":5,"ix":5},"lc":1,"lj":1,"ml":10,"bm":0,"nm":"Stroke 1","mn":"ADBE Vector Graphic - Stroke","hd":false},{"ty":"fl","c":{"a":0,"k":[1,1,1,1],"ix":4},"o":{"a":0,"k":100,"ix":5},"r":1,"bm":0,"nm":"Fill 1","mn":"ADBE Vector Graphic - Fill","hd":false},{"ty":"tr","p":{"a":0,"k":[-3206.038,782.856],"ix":2},"a":{"a":0,"k":[0,0],"ix":1},"s":{"a":0,"k":[100,100],"ix":3},"r":{"a":0,"k":0,"ix":6},"o":{"a":0,"k":100,"ix":7},"sk":{"a":0,"k":0,"ix":4},"sa":{"a":0,"k":0,"ix":5},"nm":"Transform"}],"nm":"Group 2","np":3,"cix":2,"bm":0,"ix":2,"mn":"ADBE Vector Group","hd":false},{"ty":"gr","it":[{"ind":0,"ty":"sh","ix":1,"ks":{"a":0,"k":{"i":[[-27.308,-27.308],[27.308,-27.308],[27.308,27.308],[-27.308,27.308]],"o":[[27.308,27.308],[-27.308,27.308],[-27.308,-27.308],[27.308,-27.308]],"v":[[49.446,-49.446],[49.446,49.446],[-49.446,49.446],[-49.446,-49.446]],"c":true},"ix":2},"nm":"Path 1","mn":"ADBE Vector Shape - Group","hd":false},{"ty":"st","c":{"a":0,"k":[0.01568627451,0.298039215686,0.81568627451,1],"ix":3},"o":{"a":0,"k":100,"ix":4},"w":{"a":0,"k":5,"ix":5},"lc":1,"lj":1,"ml":10,"bm":0,"nm":"Stroke 1","mn":"ADBE Vector Graphic - Stroke","hd":false},{"ty":"fl","c":{"a":0,"k":[1,1,1,1],"ix":4},"o":{"a":0,"k":100,"ix":5},"r":1,"bm":0,"nm":"Fill 1","mn":"ADBE Vector Graphic - Fill","hd":false},{"ty":"tr","p":{"a":0,"k":[-3309.924,678.97],"ix":2},"a":{"a":0,"k":[0,0],"ix":1},"s":{"a":0,"k":[100,100],"ix":3},"r":{"a":0,"k":0,"ix":6},"o":{"a":0,"k":100,"ix":7},"sk":{"a":0,"k":0,"ix":4},"sa":{"a":0,"k":0,"ix":5},"nm":"Transform"}],"nm":"Group 4","np":3,"cix":2,"bm":0,"ix":3,"mn":"ADBE Vector Group","hd":false},{"ty":"tr","p":{"a":0,"k":[-3309.924,678.97],"ix":2},"a":{"a":0,"k":[-3309.924,678.97],"ix":1},"s":{"a":0,"k":[100,100],"ix":3},"r":{"a":0,"k":0,"ix":6},"o":{"a":0,"k":100,"ix":7},"sk":{"a":0,"k":0,"ix":4},"sa":{"a":0,"k":0,"ix":5},"nm":"Transform"}],"nm":"Group 2","np":3,"cix":2,"bm":0,"ix":2,"mn":"ADBE Vector Group","hd":false}],"ip":0,"op":300,"st":0,"ct":1,"bm":0}],"markers":[],"props":{}}